MANIFEST.in
mrp_operation_data.xml
mrp_operations_demo.yml
mrp_operations_report.xml
mrp_operations_view.xml
mrp_operations_workflow.xml
mrp_operations_workflow_instance.xml
setup.py
./__init__.py
./__openerp__.py
./mrp_operations.py
./report/__init__.py
./report/mrp_code_barcode.py
./report/mrp_wc_barcode.py
./report/mrp_workorder_analysis.py
i18n/ar.po
i18n/bg.po
i18n/bs.po
i18n/ca.po
i18n/cs.po
i18n/da.po
i18n/de.po
i18n/es.po
i18n/es_AR.po
i18n/es_CR.po
i18n/es_EC.po
i18n/es_MX.po
i18n/es_VE.po
i18n/et.po
i18n/fi.po
i18n/fr.po
i18n/hi.po
i18n/hr.po
i18n/hu.po
i18n/id.po
i18n/it.po
i18n/ja.po
i18n/ko.po
i18n/lt.po
i18n/lv.po
i18n/mk.po
i18n/mn.po
i18n/mrp_operations.pot
i18n/nl.po
i18n/nl_BE.po
i18n/pl.po
i18n/pt.po
i18n/pt_BR.po
i18n/ro.po
i18n/ru.po
i18n/sl.po
i18n/sq.po
i18n/sr.po
i18n/sr@latin.po
i18n/sv.po
i18n/tlh.po
i18n/tr.po
i18n/uk.po
i18n/vi.po
i18n/zh_CN.po
i18n/zh_TW.po
images/work_order.jpeg
images/work_order_analysis.jpeg
images/work_order_planning.jpeg
openerp_mrp_operations.egg-info/PKG-INFO
openerp_mrp_operations.egg-info/SOURCES.txt
openerp_mrp_operations.egg-info/dependency_links.txt
openerp_mrp_operations.egg-info/requires.txt
openerp_mrp_operations.egg-info/top_level.txt
process/mrp_operation_process.xml
report/mrp_code_barcode.rml
report/mrp_wc_barcode.rml
report/mrp_workorder_analysis_view.xml
security/ir.model.access.csv
test/workcenter_operations.yml